releasify/__init__.py
releasify/client.py
releasify/constants.py
releasify/exceptions.py
releasify/utils.py
releasify-0.7.0.dist-info/METADATA
releasify-0.7.0.dist-info/WHEEL
releasify-0.7.0.dist-info/top_level.txt
releasify-0.7.0.dist-info/RECORD
