Metadata-Version: 2.1
Name: releasify
Version: 0.7.0
Summary: UNKNOWN
Home-page: https://github.com/steven-mercatante/releasify
Author: Steven Mercatante
Author-email: steven.mercatante@gmail.com
License: UNKNOWN
Platform: UNKNOWN
Requires-Dist: requests
